{
    "Ar36": {
        "error": 0.9028461289025925,
        "error_type": "",
        "fit": "previous",
        "references": [
            {
                "exclude": false,
                "record_id": "bu-CC-N-5984"
            }
        ],
        "value": 36.507623060039734
    },
    "Ar37": {
        "error": 2.494612372898098e-07,
        "error_type": "",
        "fit": "previous",
        "references": [
            {
                "exclude": false,
                "record_id": "bu-CC-N-5984"
            }
        ],
        "value": 1.5049870992515025e-07
    },
    "Ar38": {
        "error": 2.275676779997733e-07,
        "error_type": "",
        "fit": "previous",
        "references": [
            {
                "exclude": false,
                "record_id": "bu-CC-N-5984"
            }
        ],
        "value": 1.4684925929495453e-06
    },
    "Ar39": {
        "error": 2.7067326349392006e-07,
        "error_type": "",
        "fit": "previous",
        "references": [
            {
                "exclude": false,
                "record_id": "bu-CC-N-5984"
            }
        ],
        "value": -3.8023944224036864e-07
    },
    "Ar40": {
        "error": 3.457913644220237e-06,
        "error_type": "",
        "fit": "previous",
        "references": [
            {
                "exclude": false,
                "record_id": "bu-CC-N-5984"
            }
        ],
        "value": 0.00017288517967565436
    }
}