{
    "Ar36": {
        "error": 4.418360597411526,
        "error_type": "",
        "fit": "previous",
        "references": [
            {
                "exclude": false,
                "record_id": "bu-CC-N-2752"
            }
        ],
        "value": 2741.1810561404673
    },
    "Ar37": {
        "error": 2.9628162553684696e-07,
        "error_type": "",
        "fit": "previous",
        "references": [
            {
                "exclude": false,
                "record_id": "bu-CC-N-2752"
            }
        ],
        "value": 4.972244860740405e-06
    },
    "Ar38": {
        "error": 4.6097218736483914e-07,
        "error_type": "",
        "fit": "previous",
        "references": [
            {
                "exclude": false,
                "record_id": "bu-CC-N-2752"
            }
        ],
        "value": 9.060529842140417e-06
    },
    "Ar39": {
        "error": 4.17744063141376e-07,
        "error_type": "",
        "fit": "previous",
        "references": [
            {
                "exclude": false,
                "record_id": "bu-CC-N-2752"
            }
        ],
        "value": 1.5863850231636994e-06
    },
    "Ar40": {
        "error": 2.9717683937750937e-06,
        "error_type": "",
        "fit": "previous",
        "references": [
            {
                "exclude": false,
                "record_id": "bu-CC-N-2752"
            }
        ],
        "value": 0.01370193331513702
    }
}