{
    "Ar36": {
        "error": 1.4097250426300176,
        "error_type": "",
        "fit": "previous",
        "references": [
            {
                "exclude": false,
                "record_id": "bu-cc-N-4128"
            }
        ],
        "value": 84.06660010026364
    },
    "Ar37": {
        "error": 1.7356385805402992e-07,
        "error_type": "",
        "fit": "previous",
        "references": [
            {
                "exclude": false,
                "record_id": "bu-cc-N-4128"
            }
        ],
        "value": -6.30714133907054e-07
    },
    "Ar38": {
        "error": 1.9821053308666584e-07,
        "error_type": "",
        "fit": "previous",
        "references": [
            {
                "exclude": false,
                "record_id": "bu-cc-N-4128"
            }
        ],
        "value": 4.650704320121859e-06
    },
    "Ar39": {
        "error": 1.6438399227276702e-07,
        "error_type": "",
        "fit": "previous",
        "references": [
            {
                "exclude": false,
                "record_id": "bu-cc-N-4128"
            }
        ],
        "value": 1.0880016957681357e-07
    },
    "Ar40": {
        "error": 2.3974689188272035e-05,
        "error_type": "",
        "fit": "previous",
        "references": [
            {
                "exclude": false,
                "record_id": "bu-cc-N-4128"
            }
        ],
        "value": 0.0005139969443204174
    }
}