{
    "Ar36": {
        "error": 18.332990077792132,
        "error_type": "SEM",
        "filter_outliers_dict": {
            "filter_outliers": false,
            "iterations": 0,
            "std_devs": 0,
            "use_iqr_filtering": false,
            "use_standard_deviation_filtering": false
        },
        "fit": "linear",
        "fn": 21,
        "include_baseline_error": false,
        "n": 750,
        "outlier_excluded": [],
        "reviewed": true,
        "user_excluded": [],
        "value": 75.37539416336966
    },
    "Ar37": {
        "error": 3.8512050929901975e-06,
        "error_type": "SEM",
        "filter_outliers_dict": {
            "filter_outliers": false,
            "iterations": 0,
            "std_devs": 0,
            "use_iqr_filtering": false,
            "use_standard_deviation_filtering": false
        },
        "fit": "exponential",
        "fn": 21,
        "include_baseline_error": false,
        "n": 75,
        "outlier_excluded": [],
        "reviewed": true,
        "user_excluded": [],
        "value": 5.43088765515641e-06
    },
    "Ar38": {
        "error": 3.940541761150106e-06,
        "error_type": "SEM",
        "filter_outliers_dict": {
            "filter_outliers": false,
            "iterations": 0,
            "std_devs": 0,
            "use_iqr_filtering": false,
            "use_standard_deviation_filtering": false
        },
        "fit": "exponential",
        "fn": 21,
        "include_baseline_error": false,
        "n": 75,
        "outlier_excluded": [],
        "reviewed": true,
        "user_excluded": [],
        "value": 2.9129859134186e-05
    },
    "Ar39": {
        "error": 5.525342305706001e-06,
        "error_type": "SEM",
        "filter_outliers_dict": {
            "filter_outliers": false,
            "iterations": 0,
            "std_devs": 0,
            "use_iqr_filtering": false,
            "use_standard_deviation_filtering": false
        },
        "fit": "exponential",
        "fn": 21,
        "include_baseline_error": false,
        "n": 75,
        "outlier_excluded": [],
        "reviewed": true,
        "user_excluded": [],
        "value": 0.00103341421420348
    },
    "Ar40": {
        "error": 8.09492398528127e-06,
        "error_type": "SEM",
        "filter_outliers_dict": {
            "filter_outliers": false,
            "iterations": 0,
            "std_devs": 0,
            "use_iqr_filtering": false,
            "use_standard_deviation_filtering": false
        },
        "fit": "exponential",
        "fn": 21,
        "include_baseline_error": false,
        "n": 75,
        "outlier_excluded": [],
        "reviewed": true,
        "user_excluded": [],
        "value": 0.002661755358518673
    }
}